gaussdb_django/__init__.py
gaussdb_django/base.py
gaussdb_django/client.py
gaussdb_django/compiler.py
gaussdb_django/creation.py
gaussdb_django/expressions.py
gaussdb_django/features.py
gaussdb_django/gaussdb_any.py
gaussdb_django/introspection.py
gaussdb_django/operations.py
gaussdb_django/schema.py
gaussdb_django/fields/__init__.py
gaussdb_django-5.2.0.dist-info/licenses/LICENSE
gaussdb_django-5.2.0.dist-info/METADATA
gaussdb_django-5.2.0.dist-info/WHEEL
gaussdb_django-5.2.0.dist-info/top_level.txt
gaussdb_django-5.2.0.dist-info/RECORD
