Metadata-Version: 2.4
Name: gaussdb-django
Version: 5.2.0
Summary: Django backend for GaussDB
Project-URL: Homepage, https://github.com/HuaweiCloudDeveloper
Project-URL: Bug Reports, https://github.com/HuaweiCloudDeveloper/gaussdb-django/issues
Project-URL: Source, https://github.com/HuaweiCloudDeveloper/gaussdb-django
Classifier: Development Status :: 5 - Production/Stable
Classifier: Framework :: Django
Classifier: Framework :: Django :: 5.2
Classifier: License :: OSI Approved :: BSD License
Classifier: Operating System :: OS Independent
Classifier: Programming Language :: Python
Classifier: Programming Language :: Python :: 3
Classifier: Programming Language :: Python :: 3.10
Requires-Python: >=3.10
License-File: LICENSE
Provides-Extra: vector
Requires-Dist: numpy~=1.0; extra == "vector"
Dynamic: license-file
